COPYING
README.md
pyproject.toml
setup.cfg
setup.py
src/nqdc/__init__.py
src/nqdc/_articles.py
src/nqdc/_authors.py
src/nqdc/_commands.py
src/nqdc/_coordinate_space.py
src/nqdc/_coordinates.py
src/nqdc/_data_extraction.py
src/nqdc/_download.py
src/nqdc/_entrez.py
src/nqdc/_fit_neuroquery.py
src/nqdc/_fit_neurosynth.py
src/nqdc/_img_utils.py
src/nqdc/_labelbuddy.py
src/nqdc/_links.py
src/nqdc/_metadata.py
src/nqdc/_model_data.py
src/nqdc/_nimare.py
src/nqdc/_pipeline.py
src/nqdc/_plugins.py
src/nqdc/_text.py
src/nqdc/_typing.py
src/nqdc/_utils.py
src/nqdc/_vectorization.py
src/nqdc/_vocabulary.py
src/nqdc/_writers.py
src/nqdc.egg-info/PKG-INFO
src/nqdc.egg-info/SOURCES.txt
src/nqdc.egg-info/dependency_links.txt
src/nqdc.egg-info/entry_points.txt
src/nqdc.egg-info/not-zip-safe
src/nqdc.egg-info/requires.txt
src/nqdc.egg-info/top_level.txt
src/nqdc/_data/VERSION
src/nqdc/_data/_fit_neuroquery/README.md
src/nqdc/_data/_fit_neuroquery/app.py
src/nqdc/_data/_fit_neuroquery/requirements.txt
src/nqdc/_data/_fit_neurosynth/README.md
src/nqdc/_data/_fit_neurosynth/app.py
src/nqdc/_data/_fit_neurosynth/requirements.txt
src/nqdc/_data/stylesheets/table_extraction.xsl
src/nqdc/_data/stylesheets/text_extraction.xsl
src/nqdc/_data/stylesheets/docbook/AUTHORS
src/nqdc/_data/stylesheets/docbook/BUGS
src/nqdc/_data/stylesheets/docbook/COPYING
src/nqdc/_data/stylesheets/docbook/INSTALL
src/nqdc/_data/stylesheets/docbook/Makefile
src/nqdc/_data/stylesheets/docbook/NEWS
src/nqdc/_data/stylesheets/docbook/NEWS.html
src/nqdc/_data/stylesheets/docbook/NEWS.xml
src/nqdc/_data/stylesheets/docbook/README
src/nqdc/_data/stylesheets/docbook/RELEASE-NOTES.html
src/nqdc/_data/stylesheets/docbook/RELEASE-NOTES.txt
src/nqdc/_data/stylesheets/docbook/RELEASE-NOTES.xml
src/nqdc/_data/stylesheets/docbook/REVISION
src/nqdc/_data/stylesheets/docbook/TODO
src/nqdc/_data/stylesheets/docbook/VERSION
src/nqdc/_data/stylesheets/docbook/VERSION.xsl
src/nqdc/_data/stylesheets/docbook/build.xml
src/nqdc/_data/stylesheets/docbook/catalog.xml
src/nqdc/_data/stylesheets/docbook/install.sh
src/nqdc/_data/stylesheets/docbook/log
src/nqdc/_data/stylesheets/docbook/assembly/README
src/nqdc/_data/stylesheets/docbook/assembly/assemble.xsl
